[
    {
        "contractor": "Example Corp",
        "finance_subject": "Software Services",
        "wayOfPayment": "Wire Transfer",
        "accountManager": "John Doe",
        "currency": "USD",
        "debt_comment": "Payment pending for services rendered",
        "delay180": 1000.00,
        "delay90": 500.00,
        "delay60": 300.00,
        "delay30": 200.00,
        "delay0": 100.00,
        "delayCurrent": "No",
        "total": 2100.00,
        "totalRouble": 157500.00
    },
    {
        "contractor": "Galactic Holdings",
        "finance_subject": "Trade",
        "wayOfPayment": "Credit Card",
        "accountManager": "Leia Organa",
        "currency": "EUR",
        "debt_comment": "Outstanding balance for merchandise purchase",
        "delay180": 1500.00,
        "delay90": 700.00,
        "delay60": 400.00,
        "delay30": 300.00,
        "delay0": 200.00,
        "delayCurrent": "Yes",
        "total": 3100.00,
        "totalRouble": 237500.00
    },
    {
        "contractor": "Tycho Station Supplies",
        "finance_subject": "Equipment",
        "wayOfPayment": "Bank Transfer",
        "accountManager": "Fred Johnson",
        "currency": "GBP",
        "debt_comment": "Partial payment received, awaiting remainder",
        "delay180": 800.00,
        "delay90": 400.00,
        "delay60": 200.00,
        "delay30": 100.00,
        "delay0": 50.00,
        "delayCurrent": "No",
        "total": 1550.00,
        "totalRouble": 120000.00
    },
    {
        "contractor": "Starship Enterprises",
        "finance_subject": "Spacecraft Manufacturing",
        "wayOfPayment": "Check",
        "accountManager": "James T. Kirk",
        "currency": "USD",
        "debt_comment": "Partial payment for new starship order",
        "delay180": 2000.00,
        "delay90": 1000.00,
        "delay60": 500.00,
        "delay30": 300.00,
        "delay0": 100.00,
        "delayCurrent": "No",
        "total": 3900.00,
        "totalRouble": 292500.00
    },
    {
        "contractor": "Belt Mining Consortium",
        "finance_subject": "Mining Equipment",
        "wayOfPayment": "Bank Transfer",
        "accountManager": "Amos Burton",
        "currency": "EUR",
        "debt_comment": "Payment overdue for drill shipment",
        "delay180": 3000.00,
        "delay90": 1500.00,
        "delay60": 800.00,
        "delay30": 400.00,
        "delay0": 200.00,
        "delayCurrent": "Yes",
        "total": 5900.00,
        "totalRouble": 450000.00
    },
    {
        "contractor": "Imperial Holdings",
        "finance_subject": "Imperial Supplies",
        "wayOfPayment": "Credit Card",
        "accountManager": "Darth Vader",
        "currency": "GBP",
        "debt_comment": "Payment delayed for Sith equipment purchase",
        "delay180": 1200.00,
        "delay90": 600.00,
        "delay60": 400.00,
        "delay30": 200.00,
        "delay0": 100.00,
        "delayCurrent": "No",
        "total": 2500.00,
        "totalRouble": 192500.00
    },
    {
        "contractor": "Mandalorian Armor Inc.",
        "finance_subject": "Armor Manufacturing",
        "wayOfPayment": "PayPal",
        "accountManager": "Boba Fett",
        "currency": "USD",
        "debt_comment": "Outstanding balance for custom armor set",
        "delay180": 800.00,
        "delay90": 400.00,
        "delay60": 300.00,
        "delay30": 200.00,
        "delay0": 100.00,
        "delayCurrent": "Yes",
        "total": 1800.00,
        "totalRouble": 135000.00
    },
    {
        "contractor": "The Doctor's Clinic",
        "finance_subject": "Medical Services",
        "wayOfPayment": "Insurance",
        "accountManager": "Leonard McCoy",
        "currency": "EUR",
        "debt_comment": "Pending payment for medical treatments",
        "delay180": 500.00,
        "delay90": 200.00,
        "delay60": 100.00,
        "delay30": 50.00,
        "delay0": 25.00,
        "delayCurrent": "No",
        "total": 875.00,
        "totalRouble": 66250.00
    },
    {
        "contractor": "Resistance Armory",
        "finance_subject": "Weapons Manufacturing",
        "wayOfPayment": "Bitcoin",
        "accountManager": "Poe Dameron",
        "currency": "USD",
        "debt_comment": "Payment overdue for blaster shipment",
        "delay180": 1200.00,
        "delay90": 600.00,
        "delay60": 300.00,
        "delay30": 200.00,
        "delay0": 100.00,
        "delayCurrent": "Yes",
        "total": 2400.00,
        "totalRouble": 180000.00
    },
    {
        "contractor": "Quark's Bar and Grill",
        "finance_subject": "Food and Beverages",
        "wayOfPayment": "Cash",
        "accountManager": "Quark",
        "currency": "EUR",
        "debt_comment": "Outstanding tab for drinks and meals",
        "delay180": 300.00,
        "delay90": 150.00,
        "delay60": 100.00,
        "delay30": 50.00,
        "delay0": 25.00,
        "delayCurrent": "No",
        "total": 625.00,
        "totalRouble": 47500.00
    },
    {
        "contractor": "Nostromo Supplies",
        "finance_subject": "Spacecraft Parts",
        "wayOfPayment": "Bank Transfer",
        "accountManager": "Ellen Ripley",
        "currency": "USD",
        "debt_comment": "Payment pending for engine parts",
        "delay180": 1800.00,
        "delay90": 900.00,
        "delay60": 500.00,
        "delay30": 300.00,
        "delay0": 200.00,
        "delayCurrent": "Yes",
        "total": 3700.00,
        "totalRouble": 277500.00
    },
    {
        "contractor": "Vulcan Science Academy",
        "finance_subject": "Education Services",
        "wayOfPayment": "Wire Transfer",
        "accountManager": "Spock",
        "currency": "EUR",
        "debt_comment": "Tuition fees overdue for student",
        "delay180": 700.00,
        "delay90": 300.00,
        "delay60": 200.00,
        "delay30": 100.00,
        "delay0": 50.00,
        "delayCurrent": "No",
        "total": 1350.00,
        "totalRouble": 102500.00
    },
    {
        "contractor": "Blue Sun Corporation",
        "finance_subject": "Technology",
        "wayOfPayment": "Credit Card",
        "accountManager": "Malcolm Reynolds",
        "currency": "USD",
        "debt_comment": "Payment delayed for advanced tech components",
        "delay180": 2500.00,
        "delay90": 1200.00,
        "delay60": 700.00,
        "delay30": 400.00,
        "delay0": 200.00,
        "delayCurrent": "Yes",
        "total": 5000.00,
        "totalRouble": 375000.00
    }
]